{
  "CF122592591": {
    "contest_id": 1547,
    "language": "PyPy 3",
    "path": "codeforces\\1547\\E.py",
    "platform": "Codeforces",
    "problem_index": "E",
    "problem_name": "Air Conditioners",
    "problem_url": "https://codeforces.com/contest/1547/problem/E",
    "submission_id": "CF122592591",
    "submission_url": "https://codeforces.com/contest/1547/submission/122592591",
    "tags": [
      "data structures",
      "dp",
      "implementation",
      "shortest paths",
      "sortings",
      "two pointers",
      "*1500"
    ],
    "timestamp": "Jul/15/2021 20:02"
  },
  "CF123217749": {
    "contest_id": 15,
    "language": "GNU C++17 (64)",
    "path": "codeforces\\15\\A.cpp",
    "platform": "Codeforces",
    "problem_index": "A",
    "problem_name": "Cottage Village",
    "problem_url": "https://codeforces.com/contest/15/problem/A",
    "submission_id": "CF123217749",
    "submission_url": "https://codeforces.com/contest/15/submission/123217749",
    "tags": [
      "implementation",
      "sortings",
      "*1200"
    ],
    "timestamp": "Jul/22/2021 00:37"
  },
  "CF123246650": {
    "contest_id": 34,
    "language": "Python 3",
    "path": "codeforces\\34\\A.py",
    "platform": "Codeforces",
    "problem_index": "A",
    "problem_name": "Reconnaissance 2",
    "problem_url": "https://codeforces.com/contest/34/problem/A",
    "submission_id": "CF123246650",
    "submission_url": "https://codeforces.com/contest/34/submission/123246650",
    "tags": [
      "implementation",
      "*800"
    ],
    "timestamp": "Jul/22/2021 12:19"
  },
  "CF123246749": {
    "contest_id": 34,
    "language": "PyPy 3",
    "path": "codeforces\\34\\A.py",
    "platform": "Codeforces",
    "problem_index": "A",
    "problem_name": "Reconnaissance 2",
    "problem_url": "https://codeforces.com/contest/34/problem/A",
    "submission_id": "CF123246749",
    "submission_url": "https://codeforces.com/contest/34/submission/123246749",
    "tags": [
      "implementation",
      "*800"
    ],
    "timestamp": "Jul/22/2021 12:20"
  },
  "CF123345805": {
    "contest_id": 24,
    "language": "GNU C++17 (64)",
    "path": "codeforces\\24\\B.cpp",
    "platform": "Codeforces",
    "problem_index": "B",
    "problem_name": "F1 Champions",
    "problem_url": "https://codeforces.com/contest/24/problem/B",
    "submission_id": "CF123345805",
    "submission_url": "https://codeforces.com/contest/24/submission/123345805",
    "tags": [],
    "timestamp": "Jul/22/2021 22:46"
  },
  "CF123389183": {
    "contest_id": 24,
    "language": "GNU C++17 (64)",
    "path": "codeforces\\24\\B.cpp",
    "platform": "Codeforces",
    "problem_index": "B",
    "problem_name": "F1 Champions",
    "problem_url": "https://codeforces.com/contest/24/problem/B",
    "submission_id": "CF123389183",
    "submission_url": "https://codeforces.com/contest/24/submission/123389183",
    "tags": [
      "implementation",
      "*1500"
    ],
    "timestamp": "Jul/23/2021 10:31"
  },
  "CF123444730": {
    "contest_id": 1551,
    "language": "GNU C++17 (64)",
    "path": "codeforces\\1551\\A.cpp",
    "platform": "Codeforces",
    "problem_index": "A",
    "problem_name": "Polycarp and Coins",
    "problem_url": "https://codeforces.com/contest/1551/problem/A",
    "submission_id": "CF123444730",
    "submission_url": "https://codeforces.com/contest/1551/submission/123444730",
    "tags": [
      "greedy",
      "math",
      "*800"
    ],
    "timestamp": "Jul/23/2021 20:37"
  },
  "CF123460092": {
    "contest_id": 1551,
    "language": "GNU C++17 (64)",
    "path": "codeforces\\1551\\B1.cpp",
    "platform": "Codeforces",
    "problem_index": "B1",
    "problem_name": "Wonderful Coloring - 1",
    "problem_url": "https://codeforces.com/contest/1551/problem/B1",
    "submission_id": "CF123460092",
    "submission_url": "https://codeforces.com/contest/1551/submission/123460092",
    "tags": [
      "greedy",
      "strings",
      "*800"
    ],
    "timestamp": "Jul/23/2021 20:48"
  },
  "CF123519792": {
    "contest_id": 1551,
    "language": "GNU C++17 (64)",
    "path": "codeforces\\1551\\B2.cpp",
    "platform": "Codeforces",
    "problem_index": "B2",
    "problem_name": "Wonderful Coloring - 2",
    "problem_url": "https://codeforces.com/contest/1551/problem/B2",
    "submission_id": "CF123519792",
    "submission_url": "https://codeforces.com/contest/1551/submission/123519792",
    "tags": [
      "binary search",
      "constructive algorithms",
      "data structures",
      "greedy",
      "*1400"
    ],
    "timestamp": "Jul/23/2021 22:20"
  },
  "CF123539400": {
    "contest_id": 1551,
    "language": "GNU C++17 (64)",
    "path": "codeforces\\1551\\C.cpp",
    "platform": "Codeforces",
    "problem_index": "C",
    "problem_name": "Interesting Story",
    "problem_url": "https://codeforces.com/contest/1551/problem/C",
    "submission_id": "CF123539400",
    "submission_url": "https://codeforces.com/contest/1551/submission/123539400",
    "tags": [
      "greedy",
      "sortings",
      "strings",
      "*1500"
    ],
    "timestamp": "Jul/24/2021 00:15"
  },
  "CF123994362": {
    "contest_id": 1551,
    "language": "GNU C++17 (64)",
    "path": "codeforces\\1551\\D1.cpp",
    "platform": "Codeforces",
    "problem_index": "D1",
    "problem_name": "Domino (easy version)",
    "problem_url": "https://codeforces.com/contest/1551/problem/D1",
    "submission_id": "CF123994362",
    "submission_url": "https://codeforces.com/contest/1551/submission/123994362",
    "tags": [
      "constructive algorithms",
      "math",
      "*1700"
    ],
    "timestamp": "Jul/28/2021 11:38"
  },
  "CF124131564": {
    "contest_id": 1554,
    "language": "GNU C++17 (64)",
    "path": "codeforces\\1554\\A.cpp",
    "platform": "Codeforces",
    "problem_index": "A",
    "problem_name": "Cherry",
    "problem_url": "https://codeforces.com/contest/1554/problem/A",
    "submission_id": "CF124131564",
    "submission_url": "https://codeforces.com/contest/1554/submission/124131564",
    "tags": [
      "greedy",
      "*800"
    ],
    "timestamp": "Jul/29/2021 20:40"
  },
  "CF124293485": {
    "contest_id": 1555,
    "language": "GNU C++17 (64)",
    "path": "codeforces\\1555\\A.cpp",
    "platform": "Codeforces",
    "problem_index": "A",
    "problem_name": "PizzaForces",
    "problem_url": "https://codeforces.com/contest/1555/problem/A",
    "submission_id": "CF124293485",
    "submission_url": "https://codeforces.com/contest/1555/submission/124293485",
    "tags": [
      "brute force",
      "math",
      "*900"
    ],
    "timestamp": "Jul/30/2021 20:58"
  },
  "CF124320984": {
    "contest_id": 1555,
    "language": "GNU C++17 (64)",
    "path": "codeforces\\1555\\C.cpp",
    "platform": "Codeforces",
    "problem_index": "C",
    "problem_name": "Coin Rows",
    "problem_url": "https://codeforces.com/contest/1555/problem/C",
    "submission_id": "CF124320984",
    "submission_url": "https://codeforces.com/contest/1555/submission/124320984",
    "tags": [
      "brute force",
      "constructive algorithms",
      "dp",
      "implementation",
      "*1300"
    ],
    "timestamp": "Jul/30/2021 21:45"
  },
  "CF124333446": {
    "contest_id": 1555,
    "language": "GNU C++17 (64)",
    "path": "codeforces\\1555\\B.cpp",
    "platform": "Codeforces",
    "problem_index": "B",
    "problem_name": "Two Tables",
    "problem_url": "https://codeforces.com/contest/1555/problem/B",
    "submission_id": "CF124333446",
    "submission_url": "https://codeforces.com/contest/1555/submission/124333446",
    "tags": [
      "brute force",
      "*1300"
    ],
    "timestamp": "Jul/30/2021 22:14"
  },
  "CF125069057": {
    "contest_id": 266,
    "language": "GNU C++17 (64)",
    "path": "codeforces\\266\\B.cpp",
    "platform": "Codeforces",
    "problem_index": "B",
    "problem_name": "Queue at the School",
    "problem_url": "https://codeforces.com/contest/266/problem/B",
    "submission_id": "CF125069057",
    "submission_url": "https://codeforces.com/contest/266/submission/125069057",
    "tags": [
      "constructive algorithms",
      "graph matchings",
      "implementation",
      "shortest paths",
      "*800"
    ],
    "timestamp": "Aug/06/2021 21:45"
  },
  "CF125070418": {
    "contest_id": 339,
    "language": "GNU C++17 (64)",
    "path": "codeforces\\339\\B.cpp",
    "platform": "Codeforces",
    "problem_index": "B",
    "problem_name": "Xenia and Ringroad",
    "problem_url": "https://codeforces.com/contest/339/problem/B",
    "submission_id": "CF125070418",
    "submission_url": "https://codeforces.com/contest/339/submission/125070418",
    "tags": [
      "implementation",
      "*1000"
    ],
    "timestamp": "Aug/06/2021 22:00"
  },
  "CF125072954": {
    "contest_id": 467,
    "language": "GNU C++17 (64)",
    "path": "codeforces\\467\\B.cpp",
    "platform": "Codeforces",
    "problem_index": "B",
    "problem_name": "Fedor and New Game",
    "problem_url": "https://codeforces.com/contest/467/problem/B",
    "submission_id": "CF125072954",
    "submission_url": "https://codeforces.com/contest/467/submission/125072954",
    "tags": [
      "bitmasks",
      "brute force",
      "constructive algorithms",
      "implementation",
      "*1100"
    ],
    "timestamp": "Aug/06/2021 22:32"
  },
  "CF125077389": {
    "contest_id": 478,
    "language": "GNU C++17 (64)",
    "path": "codeforces\\478\\B.cpp",
    "platform": "Codeforces",
    "problem_index": "B",
    "problem_name": "Random Teams",
    "problem_url": "https://codeforces.com/contest/478/problem/B",
    "submission_id": "CF125077389",
    "submission_url": "https://codeforces.com/contest/478/submission/125077389",
    "tags": [
      "combinatorics",
      "constructive algorithms",
      "greedy",
      "math",
      "*1300"
    ],
    "timestamp": "Aug/06/2021 23:24"
  },
  "CF125811884": {
    "contest_id": 1554,
    "language": "GNU C++17 (64)",
    "path": "codeforces\\1554\\B.cpp",
    "platform": "Codeforces",
    "problem_index": "B",
    "problem_name": "Cobb",
    "problem_url": "https://codeforces.com/contest/1554/problem/B",
    "submission_id": "CF125811884",
    "submission_url": "https://codeforces.com/contest/1554/submission/125811884",
    "tags": [
      "bitmasks",
      "brute force",
      "greedy",
      "math",
      "*1700"
    ],
    "timestamp": "Aug/14/2021 09:37"
  },
  "CF125873094": {
    "contest_id": 492,
    "language": "GNU C++17 (64)",
    "path": "codeforces\\492\\B.cpp",
    "platform": "Codeforces",
    "problem_index": "B",
    "problem_name": "Vanya and Lanterns",
    "problem_url": "https://codeforces.com/contest/492/problem/B",
    "submission_id": "CF125873094",
    "submission_url": "https://codeforces.com/contest/492/submission/125873094",
    "tags": [
      "binary search",
      "implementation",
      "math",
      "sortings",
      "*1200"
    ],
    "timestamp": "Aug/15/2021 00:15"
  },
  "CF126556879": {
    "contest_id": 451,
    "language": "GNU C++17 (64)",
    "path": "codeforces\\451\\B.cpp",
    "platform": "Codeforces",
    "problem_index": "B",
    "problem_name": "Sort the Array",
    "problem_url": "https://codeforces.com/contest/451/problem/B",
    "submission_id": "CF126556879",
    "submission_url": "https://codeforces.com/contest/451/submission/126556879",
    "tags": [
      "implementation",
      "sortings",
      "*1300"
    ],
    "timestamp": "Aug/20/2021 22:32"
  },
  "CF126727361": {
    "contest_id": 230,
    "language": "GNU C++17 (64)",
    "path": "codeforces\\230\\B.cpp",
    "platform": "Codeforces",
    "problem_index": "B",
    "problem_name": "T-primes",
    "problem_url": "https://codeforces.com/contest/230/problem/B",
    "submission_id": "CF126727361",
    "submission_url": "https://codeforces.com/contest/230/submission/126727361",
    "tags": [
      "binary search",
      "implementation",
      "math",
      "number theory",
      "*1300"
    ],
    "timestamp": "Aug/23/2021 10:23"
  },
  "CF127341466": {
    "contest_id": 1556,
    "language": "GNU C++17 (64)",
    "path": "codeforces\\1556\\A.cpp",
    "platform": "Codeforces",
    "problem_index": "A",
    "problem_name": "A Variety of Operations",
    "problem_url": "https://codeforces.com/contest/1556/problem/A",
    "submission_id": "CF127341466",
    "submission_url": "https://codeforces.com/contest/1556/submission/127341466",
    "tags": [
      "math",
      "*800"
    ],
    "timestamp": "Aug/29/2021 20:44"
  },
  "CF127351468": {
    "contest_id": 1556,
    "language": "GNU C++17 (64)",
    "path": "codeforces\\1556\\B.cpp",
    "platform": "Codeforces",
    "problem_index": "B",
    "problem_name": "Take Your Places!",
    "problem_url": "https://codeforces.com/contest/1556/problem/B",
    "submission_id": "CF127351468",
    "submission_url": "https://codeforces.com/contest/1556/submission/127351468",
    "tags": [
      "implementation",
      "*1300"
    ],
    "timestamp": "Aug/29/2021 21:03"
  },
  "CF128090751": {
    "contest_id": 1567,
    "language": "GNU C++17 (64)",
    "path": "codeforces\\1567\\A.cpp",
    "platform": "Codeforces",
    "problem_index": "A",
    "problem_name": "Domino Disaster",
    "problem_url": "https://codeforces.com/contest/1567/problem/A",
    "submission_id": "CF128090751",
    "submission_url": "https://codeforces.com/contest/1567/submission/128090751",
    "tags": [
      "implementation",
      "strings",
      "*800"
    ],
    "timestamp": "Sep/07/2021 09:14"
  },
  "CF128308994": {
    "contest_id": 1567,
    "language": "GNU C++17 (64)",
    "path": "codeforces\\1567\\B.cpp",
    "platform": "Codeforces",
    "problem_index": "B",
    "problem_name": "MEXor Mixup",
    "problem_url": "https://codeforces.com/contest/1567/problem/B",
    "submission_id": "CF128308994",
    "submission_url": "https://codeforces.com/contest/1567/submission/128308994",
    "tags": [
      "bitmasks",
      "greedy",
      "*1000"
    ],
    "timestamp": "Sep/09/2021 09:45"
  },
  "CF129013585": {
    "contest_id": 508,
    "language": "GNU C++17 (64)",
    "path": "codeforces\\508\\B.cpp",
    "platform": "Codeforces",
    "problem_index": "B",
    "problem_name": "Anton and currency you all know",
    "problem_url": "https://codeforces.com/contest/508/problem/B",
    "submission_id": "CF129013585",
    "submission_url": "https://codeforces.com/contest/508/submission/129013585",
    "tags": [
      "greedy",
      "math",
      "strings",
      "*1300"
    ],
    "timestamp": "Sep/17/2021 00:00"
  },
  "CF129096297": {
    "contest_id": 71,
    "language": "GNU C++17 (64)",
    "path": "codeforces\\71\\A.cpp",
    "platform": "Codeforces",
    "problem_index": "A",
    "problem_name": "Way Too Long Words",
    "problem_url": "https://codeforces.com/contest/71/problem/A",
    "submission_id": "CF129096297",
    "submission_url": "https://codeforces.com/contest/71/submission/129096297",
    "tags": [
      "strings",
      "*800"
    ],
    "timestamp": "Sep/17/2021 23:29"
  },
  "CF129098149": {
    "contest_id": 339,
    "language": "GNU C++17 (64)",
    "path": "codeforces\\339\\A.cpp",
    "platform": "Codeforces",
    "problem_index": "A",
    "problem_name": "Helpful Maths",
    "problem_url": "https://codeforces.com/contest/339/problem/A",
    "submission_id": "CF129098149",
    "submission_url": "https://codeforces.com/contest/339/submission/129098149",
    "tags": [
      "greedy",
      "implementation",
      "sortings",
      "strings",
      "*800"
    ],
    "timestamp": "Sep/17/2021 23:49"
  },
  "CF129101750": {
    "contest_id": 160,
    "language": "GNU C++17 (64)",
    "path": "codeforces\\160\\A.cpp",
    "platform": "Codeforces",
    "problem_index": "A",
    "problem_name": "Twins",
    "problem_url": "https://codeforces.com/contest/160/problem/A",
    "submission_id": "CF129101750",
    "submission_url": "https://codeforces.com/contest/160/submission/129101750",
    "tags": [
      "greedy",
      "sortings",
      "*900"
    ],
    "timestamp": "Sep/18/2021 00:33"
  },
  "CF129102431": {
    "contest_id": 58,
    "language": "GNU C++17 (64)",
    "path": "codeforces\\58\\A.cpp",
    "platform": "Codeforces",
    "problem_index": "A",
    "problem_name": "Chat room",
    "problem_url": "https://codeforces.com/contest/58/problem/A",
    "submission_id": "CF129102431",
    "submission_url": "https://codeforces.com/contest/58/submission/129102431",
    "tags": [
      "greedy",
      "strings",
      "*1000"
    ],
    "timestamp": "Sep/18/2021 00:43"
  }
}