{
  "CF111726562": {
    "contest_id": 1505,
    "language": "PyPy 3",
    "path": "codeforces\\1505\\A.py",
    "platform": "Codeforces",
    "problem_index": "A",
    "problem_name": "Is it rated - 2",
    "problem_url": "https://codeforces.com/contest/1505/problem/A",
    "submission_id": "CF111726562",
    "submission_url": "https://codeforces.com/contest/1505/submission/111726562",
    "tags": [
      "*special problem",
      "implementation",
      "interactive",
      "*900"
    ],
    "timestamp": "Apr/01/2021 22:58"
  },
  "CF111726698": {
    "contest_id": 1505,
    "language": "PyPy 3",
    "path": "codeforces\\1505\\A.py",
    "platform": "Codeforces",
    "problem_index": "A",
    "problem_name": "Is it rated - 2",
    "problem_url": "https://codeforces.com/contest/1505/problem/A",
    "submission_id": "CF111726698",
    "submission_url": "https://codeforces.com/contest/1505/submission/111726698",
    "tags": [
      "*special problem",
      "implementation",
      "interactive",
      "*900"
    ],
    "timestamp": "Apr/01/2021 22:59"
  },
  "CF111802573": {
    "contest_id": 1506,
    "language": "GNU C++17 (64)",
    "path": "codeforces\\1506\\A.cpp",
    "platform": "Codeforces",
    "problem_index": "A",
    "problem_name": "Strange Table",
    "problem_url": "https://codeforces.com/contest/1506/problem/A",
    "submission_id": "CF111802573",
    "submission_url": "https://codeforces.com/contest/1506/submission/111802573",
    "tags": [
      "math",
      "*800"
    ],
    "timestamp": "Apr/02/2021 22:05"
  },
  "CF111805131": {
    "contest_id": 1506,
    "language": "GNU C++17 (64)",
    "path": "codeforces\\1506\\B.cpp",
    "platform": "Codeforces",
    "problem_index": "B",
    "problem_name": "Partial Replacement",
    "problem_url": "https://codeforces.com/contest/1506/problem/B",
    "submission_id": "CF111805131",
    "submission_url": "https://codeforces.com/contest/1506/submission/111805131",
    "tags": [
      "greedy",
      "implementation",
      "*1100"
    ],
    "timestamp": "Apr/02/2021 22:39"
  },
  "CF111805182": {
    "contest_id": 1506,
    "language": "GNU C++17 (64)",
    "path": "codeforces\\1506\\B.cpp",
    "platform": "Codeforces",
    "problem_index": "B",
    "problem_name": "Partial Replacement",
    "problem_url": "https://codeforces.com/contest/1506/problem/B",
    "submission_id": "CF111805182",
    "submission_url": "https://codeforces.com/contest/1506/submission/111805182",
    "tags": [
      "greedy",
      "implementation",
      "*1100"
    ],
    "timestamp": "Apr/02/2021 22:40"
  },
  "CF111915997": {
    "contest_id": 1504,
    "language": "GNU C++17 (64)",
    "path": "codeforces\\1504\\A.cpp",
    "platform": "Codeforces",
    "problem_index": "A",
    "problem_name": " D\u00e9j\u00e0 Vu",
    "problem_url": "https://codeforces.com/contest/1504/problem/A",
    "submission_id": "CF111915997",
    "submission_url": "https://codeforces.com/contest/1504/submission/111915997",
    "tags": [
      "constructive algorithms",
      "strings",
      "*800"
    ],
    "timestamp": "Apr/03/2021 21:52"
  },
  "CF111965796": {
    "contest_id": 1504,
    "language": "GNU C++17 (64)",
    "path": "codeforces\\1504\\C.cpp",
    "platform": "Codeforces",
    "problem_index": "C",
    "problem_name": "Balance the Bits",
    "problem_url": "https://codeforces.com/contest/1504/problem/C",
    "submission_id": "CF111965796",
    "submission_url": "https://codeforces.com/contest/1504/submission/111965796",
    "tags": [
      "brute force",
      "constructive algorithms",
      "greedy",
      "*1600"
    ],
    "timestamp": "Apr/04/2021 10:49"
  },
  "CF111972505": {
    "contest_id": 1503,
    "language": "GNU C++17 (64)",
    "path": "codeforces\\1503\\B.cpp",
    "platform": "Codeforces",
    "problem_index": "B",
    "problem_name": "3-Coloring",
    "problem_url": "https://codeforces.com/contest/1503/problem/B",
    "submission_id": "CF111972505",
    "submission_url": "https://codeforces.com/contest/1503/submission/111972505",
    "tags": [
      "constructive algorithms",
      "games",
      "interactive",
      "*1700"
    ],
    "timestamp": "Apr/04/2021 12:38"
  },
  "CF112252301": {
    "contest_id": 1504,
    "language": "GNU C++17 (64)",
    "path": "codeforces\\1504\\A.cpp",
    "platform": "Codeforces",
    "problem_index": "A",
    "problem_name": " D\u00e9j\u00e0 Vu",
    "problem_url": "https://codeforces.com/contest/1504/problem/A",
    "submission_id": "CF112252301",
    "submission_url": "https://codeforces.com/contest/1504/submission/112252301",
    "tags": [
      "constructive algorithms",
      "strings",
      "*800"
    ],
    "timestamp": "Apr/08/2021 00:16"
  },
  "CF112268400": {
    "contest_id": 1504,
    "language": "GNU C++17 (64)",
    "path": "codeforces\\1504\\B.cpp",
    "platform": "Codeforces",
    "problem_index": "B",
    "problem_name": "Flip the Bits",
    "problem_url": "https://codeforces.com/contest/1504/problem/B",
    "submission_id": "CF112268400",
    "submission_url": "https://codeforces.com/contest/1504/submission/112268400",
    "tags": [
      "constructive algorithms",
      "greedy",
      "implementation",
      "math",
      "*1200"
    ],
    "timestamp": "Apr/08/2021 08:41"
  },
  "CF112271537": {
    "contest_id": 1503,
    "language": "GNU C++17 (64)",
    "path": "codeforces\\1503\\A.cpp",
    "platform": "Codeforces",
    "problem_index": "A",
    "problem_name": "Balance the Bits",
    "problem_url": "https://codeforces.com/contest/1503/problem/A",
    "submission_id": "CF112271537",
    "submission_url": "https://codeforces.com/contest/1503/submission/112271537",
    "tags": [
      "constructive algorithms",
      "greedy",
      "*1600"
    ],
    "timestamp": "Apr/08/2021 10:26"
  },
  "CF112405605": {
    "contest_id": 1503,
    "language": "GNU C++17 (64)",
    "path": "codeforces\\1503\\B.cpp",
    "platform": "Codeforces",
    "problem_index": "B",
    "problem_name": "3-Coloring",
    "problem_url": "https://codeforces.com/contest/1503/problem/B",
    "submission_id": "CF112405605",
    "submission_url": "https://codeforces.com/contest/1503/submission/112405605",
    "tags": [
      "constructive algorithms",
      "games",
      "interactive",
      "*1700"
    ],
    "timestamp": "Apr/10/2021 00:12"
  },
  "CF112942294": {
    "contest_id": 1504,
    "language": "GNU C++17 (64)",
    "path": "codeforces\\1504\\E.cpp",
    "platform": "Codeforces",
    "problem_index": "E",
    "problem_name": "Travelling Salesman Problem",
    "problem_url": "https://codeforces.com/contest/1504/problem/E",
    "submission_id": "CF112942294",
    "submission_url": "https://codeforces.com/contest/1504/submission/112942294",
    "tags": [
      "binary search",
      "data structures",
      "dp",
      "graphs",
      "greedy",
      "shortest paths",
      "sortings",
      "*2200"
    ],
    "timestamp": "Apr/13/2021 21:48"
  },
  "CF113187987": {
    "contest_id": 1509,
    "language": "GNU C++17 (64)",
    "path": "codeforces\\1509\\A.cpp",
    "platform": "Codeforces",
    "problem_index": "A",
    "problem_name": "Average Height",
    "problem_url": "https://codeforces.com/contest/1509/problem/A",
    "submission_id": "CF113187987",
    "submission_url": "https://codeforces.com/contest/1509/submission/113187987",
    "tags": [
      "constructive algorithms",
      "*800"
    ],
    "timestamp": "Apr/16/2021 20:39"
  },
  "CF113230418": {
    "contest_id": 1509,
    "language": "GNU C++17 (64)",
    "path": "codeforces\\1509\\B.cpp",
    "platform": "Codeforces",
    "problem_index": "B",
    "problem_name": "TMT Document",
    "problem_url": "https://codeforces.com/contest/1509/problem/B",
    "submission_id": "CF113230418",
    "submission_url": "https://codeforces.com/contest/1509/submission/113230418",
    "tags": [
      "greedy",
      "*1100"
    ],
    "timestamp": "Apr/16/2021 21:41"
  },
  "CF113304238": {
    "contest_id": 1509,
    "language": "GNU C++17 (64)",
    "path": "codeforces\\1509\\D.cpp",
    "platform": "Codeforces",
    "problem_index": "D",
    "problem_name": "Binary Literature",
    "problem_url": "https://codeforces.com/contest/1509/problem/D",
    "submission_id": "CF113304238",
    "submission_url": "https://codeforces.com/contest/1509/submission/113304238",
    "tags": [
      "constructive algorithms",
      "greedy",
      "strings",
      "two pointers",
      "*1900"
    ],
    "timestamp": "Apr/17/2021 13:22"
  },
  "CF113356040": {
    "contest_id": 1111,
    "language": "GNU C++17 (64)",
    "path": "codeforces\\1111\\A.cpp",
    "platform": "Codeforces",
    "problem_index": "A",
    "problem_name": "Superhero Transformation",
    "problem_url": "https://codeforces.com/contest/1111/problem/A",
    "submission_id": "CF113356040",
    "submission_url": "https://codeforces.com/contest/1111/submission/113356040",
    "tags": [
      "implementation",
      "strings",
      "*1000"
    ],
    "timestamp": "Apr/18/2021 00:04"
  },
  "CF113357797": {
    "contest_id": 1511,
    "language": "GNU C++17 (64)",
    "path": "codeforces\\1511\\C.cpp",
    "platform": "Codeforces",
    "problem_index": "C",
    "problem_name": "Yet Another Card Deck",
    "problem_url": "https://codeforces.com/contest/1511/problem/C",
    "submission_id": "CF113357797",
    "submission_url": "https://codeforces.com/contest/1511/submission/113357797",
    "tags": [
      "brute force",
      "data structures",
      "implementation",
      "trees",
      "*1100"
    ],
    "timestamp": "Apr/18/2021 00:36"
  },
  "CF114052524": {
    "contest_id": 1514,
    "language": "GNU C++17 (64)",
    "path": "codeforces\\1514\\C.cpp",
    "platform": "Codeforces",
    "problem_index": "C",
    "problem_name": "Product 1 Modulo N",
    "problem_url": "https://codeforces.com/contest/1514/problem/C",
    "submission_id": "CF114052524",
    "submission_url": "https://codeforces.com/contest/1514/submission/114052524",
    "tags": [
      "greedy",
      "number theory",
      "*1600"
    ],
    "timestamp": "Apr/24/2021 01:43"
  },
  "CF114309485": {
    "contest_id": 1513,
    "language": "GNU C++17 (64)",
    "path": "codeforces\\1513\\A.cpp",
    "platform": "Codeforces",
    "problem_index": "A",
    "problem_name": "Array and Peaks",
    "problem_url": "https://codeforces.com/contest/1513/problem/A",
    "submission_id": "CF114309485",
    "submission_url": "https://codeforces.com/contest/1513/submission/114309485",
    "tags": [
      "constructive algorithms",
      "implementation",
      "*800"
    ],
    "timestamp": "Apr/27/2021 01:30"
  },
  "CF114468273": {
    "contest_id": 1513,
    "language": "GNU C++17 (64)",
    "path": "codeforces\\1513\\B.cpp",
    "platform": "Codeforces",
    "problem_index": "B",
    "problem_name": "AND Sequences",
    "problem_url": "https://codeforces.com/contest/1513/problem/B",
    "submission_id": "CF114468273",
    "submission_url": "https://codeforces.com/contest/1513/submission/114468273",
    "tags": [
      "bitmasks",
      "combinatorics",
      "constructive algorithms",
      "math",
      "*1400"
    ],
    "timestamp": "Apr/28/2021 22:27"
  },
  "CF114468432": {
    "contest_id": 1513,
    "language": "GNU C++17 (64)",
    "path": "codeforces\\1513\\B.cpp",
    "platform": "Codeforces",
    "problem_index": "B",
    "problem_name": "AND Sequences",
    "problem_url": "https://codeforces.com/contest/1513/problem/B",
    "submission_id": "CF114468432",
    "submission_url": "https://codeforces.com/contest/1513/submission/114468432",
    "tags": [
      "bitmasks",
      "combinatorics",
      "constructive algorithms",
      "math",
      "*1400"
    ],
    "timestamp": "Apr/28/2021 22:29"
  },
  "CF114543970": {
    "contest_id": 1519,
    "language": "GNU C++17 (64)",
    "path": "codeforces\\1519\\A.cpp",
    "platform": "Codeforces",
    "problem_index": "A",
    "problem_name": "Red and Blue Beans",
    "problem_url": "https://codeforces.com/contest/1519/problem/A",
    "submission_id": "CF114543970",
    "submission_url": "https://codeforces.com/contest/1519/submission/114543970",
    "tags": [
      "math",
      "*800"
    ],
    "timestamp": "Apr/29/2021 20:39"
  },
  "CF114567479": {
    "contest_id": 1519,
    "language": "GNU C++17 (64)",
    "path": "codeforces\\1519\\B.cpp",
    "platform": "Codeforces",
    "problem_index": "B",
    "problem_name": "The Cake Is a Lie",
    "problem_url": "https://codeforces.com/contest/1519/problem/B",
    "submission_id": "CF114567479",
    "submission_url": "https://codeforces.com/contest/1519/submission/114567479",
    "tags": [
      "dp",
      "math",
      "*800"
    ],
    "timestamp": "Apr/29/2021 21:04"
  },
  "CF114603819": {
    "contest_id": 1519,
    "language": "GNU C++17 (64)",
    "path": "codeforces\\1519\\C.cpp",
    "platform": "Codeforces",
    "problem_index": "C",
    "problem_name": "Berland Regional",
    "problem_url": "https://codeforces.com/contest/1519/problem/C",
    "submission_id": "CF114603819",
    "submission_url": "https://codeforces.com/contest/1519/submission/114603819",
    "tags": [
      "brute force",
      "data structures",
      "greedy",
      "number theory",
      "sortings",
      "*1400"
    ],
    "timestamp": "Apr/29/2021 22:12"
  },
  "CF114793237": {
    "contest_id": 1519,
    "language": "GNU C++17 (64)",
    "path": "codeforces\\1519\\C.cpp",
    "platform": "Codeforces",
    "problem_index": "C",
    "problem_name": "Berland Regional",
    "problem_url": "https://codeforces.com/contest/1519/problem/C",
    "submission_id": "CF114793237",
    "submission_url": "https://codeforces.com/contest/1519/submission/114793237",
    "tags": [
      "brute force",
      "data structures",
      "greedy",
      "number theory",
      "sortings",
      "*1400"
    ],
    "timestamp": "May/01/2021 22:57"
  },
  "CF115066622": {
    "contest_id": 922,
    "language": "GNU C++17 (64)",
    "path": "codeforces\\922\\A.cpp",
    "platform": "Codeforces",
    "problem_index": "A",
    "problem_name": "Cloning Toys",
    "problem_url": "https://codeforces.com/contest/922/problem/A",
    "submission_id": "CF115066622",
    "submission_url": "https://codeforces.com/contest/922/submission/115066622",
    "tags": [
      "implementation",
      "*1300"
    ],
    "timestamp": "May/04/2021 01:56"
  },
  "CF115125972": {
    "contest_id": 39,
    "language": "GNU C++17 (64)",
    "path": "codeforces\\39\\H.cpp",
    "platform": "Codeforces",
    "problem_index": "H",
    "problem_name": "Multiplication Table",
    "problem_url": "https://codeforces.com/contest/39/problem/H",
    "submission_id": "CF115125972",
    "submission_url": "https://codeforces.com/contest/39/submission/115125972",
    "tags": [
      "implementation",
      "*1300"
    ],
    "timestamp": "May/04/2021 21:06"
  },
  "CF115150379": {
    "contest_id": 276,
    "language": "GNU C++17 (64)",
    "path": "codeforces\\276\\B.cpp",
    "platform": "Codeforces",
    "problem_index": "B",
    "problem_name": "Little Girl and Game",
    "problem_url": "https://codeforces.com/contest/276/problem/B",
    "submission_id": "CF115150379",
    "submission_url": "https://codeforces.com/contest/276/submission/115150379",
    "tags": [
      "games",
      "greedy",
      "*1300"
    ],
    "timestamp": "May/05/2021 02:55"
  },
  "CF115199088": {
    "contest_id": 241,
    "language": "GNU C++17 (64)",
    "path": "codeforces\\241\\A.cpp",
    "platform": "Codeforces",
    "problem_index": "A",
    "problem_name": "Old Peykan",
    "problem_url": "https://codeforces.com/contest/241/problem/A",
    "submission_id": "CF115199088",
    "submission_url": "https://codeforces.com/contest/241/submission/115199088",
    "tags": [
      "greedy",
      "*1300"
    ],
    "timestamp": "May/05/2021 17:44"
  },
  "CF115212168": {
    "contest_id": 1159,
    "language": "GNU C++17 (64)",
    "path": "codeforces\\1159\\B.cpp",
    "platform": "Codeforces",
    "problem_index": "B",
    "problem_name": "Expansion coefficient of the array",
    "problem_url": "https://codeforces.com/contest/1159/problem/B",
    "submission_id": "CF115212168",
    "submission_url": "https://codeforces.com/contest/1159/submission/115212168",
    "tags": [
      "implementation",
      "math",
      "*1300"
    ],
    "timestamp": "May/05/2021 20:31"
  },
  "CF115442982": {
    "contest_id": 1520,
    "language": "GNU C++17 (64)",
    "path": "codeforces\\1520\\A.cpp",
    "platform": "Codeforces",
    "problem_index": "A",
    "problem_name": "Do Not Be Distracted!",
    "problem_url": "https://codeforces.com/contest/1520/problem/A",
    "submission_id": "CF115442982",
    "submission_url": "https://codeforces.com/contest/1520/submission/115442982",
    "tags": [
      "brute force",
      "implementation",
      "*800"
    ],
    "timestamp": "May/06/2021 23:10"
  },
  "CF115444389": {
    "contest_id": 1520,
    "language": "GNU C++17 (64)",
    "path": "codeforces\\1520\\B.cpp",
    "platform": "Codeforces",
    "problem_index": "B",
    "problem_name": "Ordinary Numbers",
    "problem_url": "https://codeforces.com/contest/1520/problem/B",
    "submission_id": "CF115444389",
    "submission_url": "https://codeforces.com/contest/1520/submission/115444389",
    "tags": [
      "brute force",
      "math",
      "number theory",
      "*800"
    ],
    "timestamp": "May/06/2021 23:27"
  },
  "CF115447029": {
    "contest_id": 1520,
    "language": "GNU C++17 (64)",
    "path": "codeforces\\1520\\C.cpp",
    "platform": "Codeforces",
    "problem_index": "C",
    "problem_name": "Not Adjacent Matrix",
    "problem_url": "https://codeforces.com/contest/1520/problem/C",
    "submission_id": "CF115447029",
    "submission_url": "https://codeforces.com/contest/1520/submission/115447029",
    "tags": [
      "constructive algorithms",
      "*1000"
    ],
    "timestamp": "May/06/2021 23:59"
  },
  "CF115449037": {
    "contest_id": 1520,
    "language": "GNU C++17 (64)",
    "path": "codeforces\\1520\\D.cpp",
    "platform": "Codeforces",
    "problem_index": "D",
    "problem_name": "Same Differences",
    "problem_url": "https://codeforces.com/contest/1520/problem/D",
    "submission_id": "CF115449037",
    "submission_url": "https://codeforces.com/contest/1520/submission/115449037",
    "tags": [
      "data structures",
      "hashing",
      "math",
      "*1200"
    ],
    "timestamp": "May/07/2021 00:25"
  },
  "CF115457863": {
    "contest_id": 1520,
    "language": "GNU C++17 (64)",
    "path": "codeforces\\1520\\E.cpp",
    "platform": "Codeforces",
    "problem_index": "E",
    "problem_name": "Arranging The Sheep",
    "problem_url": "https://codeforces.com/contest/1520/problem/E",
    "submission_id": "CF115457863",
    "submission_url": "https://codeforces.com/contest/1520/submission/115457863",
    "tags": [
      "greedy",
      "math",
      "*1400"
    ],
    "timestamp": "May/07/2021 02:38"
  },
  "CF115630749": {
    "contest_id": 1520,
    "language": "GNU C++17 (64)",
    "path": "codeforces\\1520\\F1.cpp",
    "platform": "Codeforces",
    "problem_index": "F1",
    "problem_name": "Guess the K-th Zero (Easy version)",
    "problem_url": "https://codeforces.com/contest/1520/problem/F1",
    "submission_id": "CF115630749",
    "submission_url": "https://codeforces.com/contest/1520/submission/115630749",
    "tags": [
      "binary search",
      "interactive",
      "*1600"
    ],
    "timestamp": "May/08/2021 01:04"
  },
  "CF115729789": {
    "contest_id": 472,
    "language": "GNU C++17 (64)",
    "path": "codeforces\\472\\A.cpp",
    "platform": "Codeforces",
    "problem_index": "A",
    "problem_name": "Design Tutorial: Learn from Math",
    "problem_url": "https://codeforces.com/contest/472/problem/A",
    "submission_id": "CF115729789",
    "submission_url": "https://codeforces.com/contest/472/submission/115729789",
    "tags": [
      "math",
      "number theory",
      "*800"
    ],
    "timestamp": "May/09/2021 00:14"
  },
  "CF115730097": {
    "contest_id": 472,
    "language": "GNU C++17 (64)",
    "path": "codeforces\\472\\A.cpp",
    "platform": "Codeforces",
    "problem_index": "A",
    "problem_name": "Design Tutorial: Learn from Math",
    "problem_url": "https://codeforces.com/contest/472/problem/A",
    "submission_id": "CF115730097",
    "submission_url": "https://codeforces.com/contest/472/submission/115730097",
    "tags": [
      "math",
      "number theory",
      "*800"
    ],
    "timestamp": "May/09/2021 00:18"
  },
  "CF115730653": {
    "contest_id": 499,
    "language": "GNU C++17 (64)",
    "path": "codeforces\\499\\B.cpp",
    "platform": "Codeforces",
    "problem_index": "B",
    "problem_name": "Lecture",
    "problem_url": "https://codeforces.com/contest/499/problem/B",
    "submission_id": "CF115730653",
    "submission_url": "https://codeforces.com/contest/499/submission/115730653",
    "tags": [
      "implementation",
      "strings",
      "*1000"
    ],
    "timestamp": "May/09/2021 00:27"
  },
  "CF115731404": {
    "contest_id": 690,
    "language": "GNU C++17 (64)",
    "path": "codeforces\\690\\D1.cpp",
    "platform": "Codeforces",
    "problem_index": "D1",
    "problem_name": "The Wall (easy)",
    "problem_url": "https://codeforces.com/contest/690/problem/D1",
    "submission_id": "CF115731404",
    "submission_url": "https://codeforces.com/contest/690/submission/115731404",
    "tags": [
      "*1200"
    ],
    "timestamp": "May/09/2021 00:40"
  },
  "CF115771663": {
    "contest_id": 6,
    "language": "GNU C++17 (64)",
    "path": "codeforces\\6\\A.cpp",
    "platform": "Codeforces",
    "problem_index": "A",
    "problem_name": "Triangle",
    "problem_url": "https://codeforces.com/contest/6/problem/A",
    "submission_id": "CF115771663",
    "submission_url": "https://codeforces.com/contest/6/submission/115771663",
    "tags": [
      "brute force",
      "geometry",
      "*900"
    ],
    "timestamp": "May/09/2021 15:00"
  },
  "CF115892453": {
    "contest_id": 1082,
    "language": "GNU C++17 (64)",
    "path": "codeforces\\1082\\A.cpp",
    "platform": "Codeforces",
    "problem_index": "A",
    "problem_name": "Vasya and Book",
    "problem_url": "https://codeforces.com/contest/1082/problem/A",
    "submission_id": "CF115892453",
    "submission_url": "https://codeforces.com/contest/1082/submission/115892453",
    "tags": [
      "implementation",
      "math",
      "*1200"
    ],
    "timestamp": "May/11/2021 01:00"
  },
  "CF115896344": {
    "contest_id": 1100,
    "language": "GNU C++17 (64)",
    "path": "codeforces\\1100\\C.cpp",
    "platform": "Codeforces",
    "problem_index": "C",
    "problem_name": "NN and the Optical Illusion",
    "problem_url": "https://codeforces.com/contest/1100/problem/C",
    "submission_id": "CF115896344",
    "submission_url": "https://codeforces.com/contest/1100/submission/115896344",
    "tags": [
      "binary search",
      "geometry",
      "math",
      "*1200"
    ],
    "timestamp": "May/11/2021 02:32"
  },
  "CF115973629": {
    "contest_id": 639,
    "language": "GNU C++17 (64)",
    "path": "codeforces\\639\\A.cpp",
    "platform": "Codeforces",
    "problem_index": "A",
    "problem_name": "Bear and Displayed Friends",
    "problem_url": "https://codeforces.com/contest/639/problem/A",
    "submission_id": "CF115973629",
    "submission_url": "https://codeforces.com/contest/639/submission/115973629",
    "tags": [
      "implementation",
      "*1200"
    ],
    "timestamp": "May/12/2021 01:19"
  },
  "CF116021310": {
    "contest_id": 1513,
    "language": "GNU C++17 (64)",
    "path": "codeforces\\1513\\C.cpp",
    "platform": "Codeforces",
    "problem_index": "C",
    "problem_name": "Add One",
    "problem_url": "https://codeforces.com/contest/1513/problem/C",
    "submission_id": "CF116021310",
    "submission_url": "https://codeforces.com/contest/1513/submission/116021310",
    "tags": [
      "dp",
      "matrices",
      "*1600"
    ],
    "timestamp": "May/12/2021 17:51"
  },
  "CF116021985": {
    "contest_id": 1513,
    "language": "GNU C++17 (64)",
    "path": "codeforces\\1513\\C.cpp",
    "platform": "Codeforces",
    "problem_index": "C",
    "problem_name": "Add One",
    "problem_url": "https://codeforces.com/contest/1513/problem/C",
    "submission_id": "CF116021985",
    "submission_url": "https://codeforces.com/contest/1513/submission/116021985",
    "tags": [
      "dp",
      "matrices",
      "*1600"
    ],
    "timestamp": "May/12/2021 17:58"
  },
  "CF116053114": {
    "contest_id": 931,
    "language": "GNU C++17 (64)",
    "path": "codeforces\\931\\B.cpp",
    "platform": "Codeforces",
    "problem_index": "B",
    "problem_name": "World Cup",
    "problem_url": "https://codeforces.com/contest/931/problem/B",
    "submission_id": "CF116053114",
    "submission_url": "https://codeforces.com/contest/931/submission/116053114",
    "tags": [
      "constructive algorithms",
      "implementation",
      "*1200"
    ],
    "timestamp": "May/13/2021 00:17"
  },
  "CF116271739": {
    "contest_id": 1516,
    "language": "GNU C++17 (64)",
    "path": "codeforces\\1516\\A.cpp",
    "platform": "Codeforces",
    "problem_index": "A",
    "problem_name": "Tit for Tat",
    "problem_url": "https://codeforces.com/contest/1516/problem/A",
    "submission_id": "CF116271739",
    "submission_url": "https://codeforces.com/contest/1516/submission/116271739",
    "tags": [
      "greedy",
      "*800"
    ],
    "timestamp": "May/15/2021 20:43"
  },
  "CF116307669": {
    "contest_id": 4,
    "language": "PyPy 3",
    "path": "codeforces\\4\\A.py",
    "platform": "Codeforces",
    "problem_index": "A",
    "problem_name": "Watermelon",
    "problem_url": "https://codeforces.com/contest/4/problem/A",
    "submission_id": "CF116307669",
    "submission_url": "https://codeforces.com/contest/4/submission/116307669",
    "tags": [
      "brute force",
      "math",
      "*800"
    ],
    "timestamp": "May/16/2021 10:53"
  },
  "CF116498629": {
    "contest_id": 25,
    "language": "GNU C++17 (64)",
    "path": "codeforces\\25\\B.cpp",
    "platform": "Codeforces",
    "problem_index": "B",
    "problem_name": "Phone numbers",
    "problem_url": "https://codeforces.com/contest/25/problem/B",
    "submission_id": "CF116498629",
    "submission_url": "https://codeforces.com/contest/25/submission/116498629",
    "tags": [
      "implementation",
      "*1100"
    ],
    "timestamp": "May/17/2021 21:50"
  },
  "CF116501929": {
    "contest_id": 9,
    "language": "GNU C++17 (64)",
    "path": "codeforces\\9\\A.cpp",
    "platform": "Codeforces",
    "problem_index": "A",
    "problem_name": "Die Roll",
    "problem_url": "https://codeforces.com/contest/9/problem/A",
    "submission_id": "CF116501929",
    "submission_url": "https://codeforces.com/contest/9/submission/116501929",
    "tags": [
      "math",
      "probabilities",
      "*800"
    ],
    "timestamp": "May/17/2021 22:29"
  },
  "CF116591655": {
    "contest_id": 5,
    "language": "PyPy 3",
    "path": "codeforces\\5\\B.py",
    "platform": "Codeforces",
    "problem_index": "B",
    "problem_name": "Center Alignment",
    "problem_url": "https://codeforces.com/contest/5/problem/B",
    "submission_id": "CF116591655",
    "submission_url": "https://codeforces.com/contest/5/submission/116591655",
    "tags": [
      "implementation",
      "strings",
      "*1200"
    ],
    "timestamp": "May/18/2021 23:29"
  },
  "CF116591957": {
    "contest_id": 5,
    "language": "PyPy 3",
    "path": "codeforces\\5\\B.py",
    "platform": "Codeforces",
    "problem_index": "B",
    "problem_name": "Center Alignment",
    "problem_url": "https://codeforces.com/contest/5/problem/B",
    "submission_id": "CF116591957",
    "submission_url": "https://codeforces.com/contest/5/submission/116591957",
    "tags": [
      "implementation",
      "strings",
      "*1200"
    ],
    "timestamp": "May/18/2021 23:33"
  },
  "CF116593524": {
    "contest_id": 25,
    "language": "PyPy 3",
    "path": "codeforces\\25\\A.py",
    "platform": "Codeforces",
    "problem_index": "A",
    "problem_name": "IQ test",
    "problem_url": "https://codeforces.com/contest/25/problem/A",
    "submission_id": "CF116593524",
    "submission_url": "https://codeforces.com/contest/25/submission/116593524",
    "tags": [
      "brute force",
      "*1300"
    ],
    "timestamp": "May/18/2021 23:54"
  },
  "CF116596175": {
    "contest_id": 26,
    "language": "PyPy 3",
    "path": "codeforces\\26\\A.py",
    "platform": "Codeforces",
    "problem_index": "A",
    "problem_name": "Almost Prime",
    "problem_url": "https://codeforces.com/contest/26/problem/A",
    "submission_id": "CF116596175",
    "submission_url": "https://codeforces.com/contest/26/submission/116596175",
    "tags": [
      "number theory",
      "*900"
    ],
    "timestamp": "May/19/2021 00:33"
  },
  "CF116597722": {
    "contest_id": 11,
    "language": "PyPy 3",
    "path": "codeforces\\11\\A.py",
    "platform": "Codeforces",
    "problem_index": "A",
    "problem_name": "Increasing Sequence",
    "problem_url": "https://codeforces.com/contest/11/problem/A",
    "submission_id": "CF116597722",
    "submission_url": "https://codeforces.com/contest/11/submission/116597722",
    "tags": [
      "constructive algorithms",
      "implementation",
      "math",
      "*900"
    ],
    "timestamp": "May/19/2021 00:58"
  },
  "CF116598787": {
    "contest_id": 6,
    "language": "PyPy 3",
    "path": "codeforces\\6\\B.py",
    "platform": "Codeforces",
    "problem_index": "B",
    "problem_name": "President's Office",
    "problem_url": "https://codeforces.com/contest/6/problem/B",
    "submission_id": "CF116598787",
    "submission_url": "https://codeforces.com/contest/6/submission/116598787",
    "tags": [
      "implementation",
      "*1100"
    ],
    "timestamp": "May/19/2021 01:18"
  },
  "CF116598897": {
    "contest_id": 6,
    "language": "PyPy 3",
    "path": "codeforces\\6\\B.py",
    "platform": "Codeforces",
    "problem_index": "B",
    "problem_name": "President's Office",
    "problem_url": "https://codeforces.com/contest/6/problem/B",
    "submission_id": "CF116598897",
    "submission_url": "https://codeforces.com/contest/6/submission/116598897",
    "tags": [
      "implementation",
      "*1100"
    ],
    "timestamp": "May/19/2021 01:21"
  },
  "CF116599916": {
    "contest_id": 6,
    "language": "PyPy 3",
    "path": "codeforces\\6\\C.py",
    "platform": "Codeforces",
    "problem_index": "C",
    "problem_name": "Alice, Bob and Chocolate",
    "problem_url": "https://codeforces.com/contest/6/problem/C",
    "submission_id": "CF116599916",
    "submission_url": "https://codeforces.com/contest/6/submission/116599916",
    "tags": [
      "greedy",
      "two pointers",
      "*1200"
    ],
    "timestamp": "May/19/2021 01:39"
  },
  "CF116684148": {
    "contest_id": 3,
    "language": "PyPy 3",
    "path": "codeforces\\3\\A.py",
    "platform": "Codeforces",
    "problem_index": "A",
    "problem_name": "Shortest path of the king",
    "problem_url": "https://codeforces.com/contest/3/problem/A",
    "submission_id": "CF116684148",
    "submission_url": "https://codeforces.com/contest/3/submission/116684148",
    "tags": [
      "greedy",
      "shortest paths",
      "*1000"
    ],
    "timestamp": "May/20/2021 00:03"
  },
  "CF117041807": {
    "contest_id": 1527,
    "language": "PyPy 3",
    "path": "codeforces\\1527\\A.py",
    "platform": "Codeforces",
    "problem_index": "A",
    "problem_name": "And Then There Were K",
    "problem_url": "https://codeforces.com/contest/1527/problem/A",
    "submission_id": "CF117041807",
    "submission_url": "https://codeforces.com/contest/1527/submission/117041807",
    "tags": [
      "bitmasks",
      "*800"
    ],
    "timestamp": "May/23/2021 00:37"
  },
  "CF117351359": {
    "contest_id": 16,
    "language": "PyPy 3",
    "path": "codeforces\\16\\B.py",
    "platform": "Codeforces",
    "problem_index": "B",
    "problem_name": "Burglar and Matches",
    "problem_url": "https://codeforces.com/contest/16/problem/B",
    "submission_id": "CF117351359",
    "submission_url": "https://codeforces.com/contest/16/submission/117351359",
    "tags": [
      "greedy",
      "implementation",
      "sortings",
      "*900"
    ],
    "timestamp": "May/26/2021 00:34"
  },
  "CF117525439": {
    "contest_id": 31,
    "language": "PyPy 3",
    "path": "codeforces\\31\\A.py",
    "platform": "Codeforces",
    "problem_index": "A",
    "problem_name": "Worms Evolution",
    "problem_url": "https://codeforces.com/contest/31/problem/A",
    "submission_id": "CF117525439",
    "submission_url": "https://codeforces.com/contest/31/submission/117525439",
    "tags": [
      "implementation",
      "*1200"
    ],
    "timestamp": "May/27/2021 23:46"
  },
  "CF117525563": {
    "contest_id": 31,
    "language": "PyPy 3",
    "path": "codeforces\\31\\A.py",
    "platform": "Codeforces",
    "problem_index": "A",
    "problem_name": "Worms Evolution",
    "problem_url": "https://codeforces.com/contest/31/problem/A",
    "submission_id": "CF117525563",
    "submission_url": "https://codeforces.com/contest/31/submission/117525563",
    "tags": [
      "implementation",
      "*1200"
    ],
    "timestamp": "May/27/2021 23:47"
  },
  "CF117527461": {
    "contest_id": 31,
    "language": "PyPy 3",
    "path": "codeforces\\31\\B.py",
    "platform": "Codeforces",
    "problem_index": "B",
    "problem_name": "Sysadmin Bob",
    "problem_url": "https://codeforces.com/contest/31/problem/B",
    "submission_id": "CF117527461",
    "submission_url": "https://codeforces.com/contest/31/submission/117527461",
    "tags": [
      "greedy",
      "implementation",
      "strings",
      "*1500"
    ],
    "timestamp": "May/28/2021 00:11"
  },
  "CF117552200": {
    "contest_id": 66,
    "language": "PyPy 3",
    "path": "codeforces\\66\\A.py",
    "platform": "Codeforces",
    "problem_index": "A",
    "problem_name": "Petya and Java",
    "problem_url": "https://codeforces.com/contest/66/problem/A",
    "submission_id": "CF117552200",
    "submission_url": "https://codeforces.com/contest/66/submission/117552200",
    "tags": [
      "implementation",
      "strings",
      "*1300"
    ],
    "timestamp": "May/28/2021 11:19"
  },
  "CF118115499": {
    "contest_id": 69,
    "language": "GNU C++17 (64)",
    "path": "codeforces\\69\\A.cpp",
    "platform": "Codeforces",
    "problem_index": "A",
    "problem_name": "Young Physicist",
    "problem_url": "https://codeforces.com/contest/69/problem/A",
    "submission_id": "CF118115499",
    "submission_url": "https://codeforces.com/contest/69/submission/118115499",
    "tags": [
      "implementation",
      "math",
      "*1000"
    ],
    "timestamp": "Jun/01/2021 21:37"
  },
  "CF118217516": {
    "contest_id": 34,
    "language": "PyPy 3",
    "path": "codeforces\\34\\B.py",
    "platform": "Codeforces",
    "problem_index": "B",
    "problem_name": "Sale",
    "problem_url": "https://codeforces.com/contest/34/problem/B",
    "submission_id": "CF118217516",
    "submission_url": "https://codeforces.com/contest/34/submission/118217516",
    "tags": [
      "greedy",
      "sortings",
      "*900"
    ],
    "timestamp": "Jun/02/2021 23:22"
  },
  "CF118217591": {
    "contest_id": 34,
    "language": "PyPy 3",
    "path": "codeforces\\34\\B.py",
    "platform": "Codeforces",
    "problem_index": "B",
    "problem_name": "Sale",
    "problem_url": "https://codeforces.com/contest/34/problem/B",
    "submission_id": "CF118217591",
    "submission_url": "https://codeforces.com/contest/34/submission/118217591",
    "tags": [
      "greedy",
      "sortings",
      "*900"
    ],
    "timestamp": "Jun/02/2021 23:23"
  },
  "CF118221399": {
    "contest_id": 69,
    "language": "PyPy 3",
    "path": "codeforces\\69\\B.py",
    "platform": "Codeforces",
    "problem_index": "B",
    "problem_name": "Bets",
    "problem_url": "https://codeforces.com/contest/69/problem/B",
    "submission_id": "CF118221399",
    "submission_url": "https://codeforces.com/contest/69/submission/118221399",
    "tags": [
      "greedy",
      "implementation",
      "*1200"
    ],
    "timestamp": "Jun/03/2021 00:16"
  },
  "CF118223726": {
    "contest_id": 70,
    "language": "PyPy 3",
    "path": "codeforces\\70\\A.py",
    "platform": "Codeforces",
    "problem_index": "A",
    "problem_name": "Cookies",
    "problem_url": "https://codeforces.com/contest/70/problem/A",
    "submission_id": "CF118223726",
    "submission_url": "https://codeforces.com/contest/70/submission/118223726",
    "tags": [
      "math",
      "*1300"
    ],
    "timestamp": "Jun/03/2021 00:55"
  },
  "CF118754727": {
    "contest_id": 1535,
    "language": "GNU C++17 (64)",
    "path": "codeforces\\1535\\A.cpp",
    "platform": "Codeforces",
    "problem_index": "A",
    "problem_name": "Fair Playoff",
    "problem_url": "https://codeforces.com/contest/1535/problem/A",
    "submission_id": "CF118754727",
    "submission_url": "https://codeforces.com/contest/1535/submission/118754727",
    "tags": [
      "brute force",
      "implementation",
      "*800"
    ],
    "timestamp": "Jun/08/2021 01:52"
  },
  "CF118755885": {
    "contest_id": 1535,
    "language": "GNU C++17 (64)",
    "path": "codeforces\\1535\\B.cpp",
    "platform": "Codeforces",
    "problem_index": "B",
    "problem_name": "Array Reodering",
    "problem_url": "https://codeforces.com/contest/1535/problem/B",
    "submission_id": "CF118755885",
    "submission_url": "https://codeforces.com/contest/1535/submission/118755885",
    "tags": [
      "brute force",
      "greedy",
      "math",
      "number theory",
      "sortings",
      "*900"
    ],
    "timestamp": "Jun/08/2021 02:21"
  },
  "CF118756121": {
    "contest_id": 1535,
    "language": "GNU C++17 (64)",
    "path": "codeforces\\1535\\B.cpp",
    "platform": "Codeforces",
    "problem_index": "B",
    "problem_name": "Array Reodering",
    "problem_url": "https://codeforces.com/contest/1535/problem/B",
    "submission_id": "CF118756121",
    "submission_url": "https://codeforces.com/contest/1535/submission/118756121",
    "tags": [
      "brute force",
      "greedy",
      "math",
      "number theory",
      "sortings",
      "*900"
    ],
    "timestamp": "Jun/08/2021 02:27"
  },
  "CF119874904": {
    "contest_id": 1535,
    "language": "GNU C++17 (64)",
    "path": "codeforces\\1535\\C.cpp",
    "platform": "Codeforces",
    "problem_index": "C",
    "problem_name": "Unstable String",
    "problem_url": "https://codeforces.com/contest/1535/problem/C",
    "submission_id": "CF119874904",
    "submission_url": "https://codeforces.com/contest/1535/submission/119874904",
    "tags": [
      "binary search",
      "dp",
      "greedy",
      "implementation",
      "strings",
      "two pointers",
      "*1400"
    ],
    "timestamp": "Jun/18/2021 21:51"
  },
  "CF119950730": {
    "contest_id": 23,
    "language": "GNU C++17 (64)",
    "path": "codeforces\\23\\A.cpp",
    "platform": "Codeforces",
    "problem_index": "A",
    "problem_name": "You're Given a String...",
    "problem_url": "https://codeforces.com/contest/23/problem/A",
    "submission_id": "CF119950730",
    "submission_url": "https://codeforces.com/contest/23/submission/119950730",
    "tags": [
      "brute force",
      "greedy",
      "*1200"
    ],
    "timestamp": "Jun/19/2021 11:24"
  },
  "CF120007330": {
    "contest_id": 4,
    "language": "GNU C++17 (64)",
    "path": "codeforces\\4\\C.cpp",
    "platform": "Codeforces",
    "problem_index": "C",
    "problem_name": "Registration System",
    "problem_url": "https://codeforces.com/contest/4/problem/C",
    "submission_id": "CF120007330",
    "submission_url": "https://codeforces.com/contest/4/submission/120007330",
    "tags": [
      "data structures",
      "hashing",
      "implementation",
      "*1300"
    ],
    "timestamp": "Jun/19/2021 21:39"
  },
  "CF120206541": {
    "contest_id": 1490,
    "language": "GNU C++17 (64)",
    "path": "codeforces\\1490\\B.cpp",
    "platform": "Codeforces",
    "problem_index": "B",
    "problem_name": "Balanced Remainders",
    "problem_url": "https://codeforces.com/contest/1490/problem/B",
    "submission_id": "CF120206541",
    "submission_url": "https://codeforces.com/contest/1490/submission/120206541",
    "tags": [
      "brute force",
      "constructive algorithms",
      "math",
      "*1000"
    ],
    "timestamp": "Jun/21/2021 18:19"
  },
  "CF122015128": {
    "contest_id": 1547,
    "language": "GNU C++17 (64)",
    "path": "codeforces\\1547\\A.cpp",
    "platform": "Codeforces",
    "problem_index": "A",
    "problem_name": "Shortest Path with Obstacle",
    "problem_url": "https://codeforces.com/contest/1547/problem/A",
    "submission_id": "CF122015128",
    "submission_url": "https://codeforces.com/contest/1547/submission/122015128",
    "tags": [
      "implementation",
      "math",
      "*800"
    ],
    "timestamp": "Jul/11/2021 00:59"
  },
  "CF122016710": {
    "contest_id": 1547,
    "language": "GNU C++17 (64)",
    "path": "codeforces\\1547\\B.cpp",
    "platform": "Codeforces",
    "problem_index": "B",
    "problem_name": "Alphabetical Strings",
    "problem_url": "https://codeforces.com/contest/1547/problem/B",
    "submission_id": "CF122016710",
    "submission_url": "https://codeforces.com/contest/1547/submission/122016710",
    "tags": [
      "greedy",
      "implementation",
      "strings",
      "*800"
    ],
    "timestamp": "Jul/11/2021 01:25"
  },
  "CF122020455": {
    "contest_id": 1547,
    "language": "GNU C++17 (64)",
    "path": "codeforces\\1547\\C.cpp",
    "platform": "Codeforces",
    "problem_index": "C",
    "problem_name": "Pair Programming",
    "problem_url": "https://codeforces.com/contest/1547/problem/C",
    "submission_id": "CF122020455",
    "submission_url": "https://codeforces.com/contest/1547/submission/122020455",
    "tags": [
      "greedy",
      "two pointers",
      "*1100"
    ],
    "timestamp": "Jul/11/2021 02:44"
  },
  "CF122036806": {
    "contest_id": 1547,
    "language": "GNU C++17 (64)",
    "path": "codeforces\\1547\\D.cpp",
    "platform": "Codeforces",
    "problem_index": "D",
    "problem_name": "Co-growing Sequence",
    "problem_url": "https://codeforces.com/contest/1547/problem/D",
    "submission_id": "CF122036806",
    "submission_url": "https://codeforces.com/contest/1547/submission/122036806",
    "tags": [
      "bitmasks",
      "constructive algorithms",
      "greedy",
      "*1300"
    ],
    "timestamp": "Jul/11/2021 10:58"
  },
  "CF122592591": {
    "contest_id": 1547,
    "language": "PyPy 3",
    "path": "codeforces\\1547\\E.py",
    "platform": "Codeforces",
    "problem_index": "E",
    "problem_name": "Air Conditioners",
    "problem_url": "https://codeforces.com/contest/1547/problem/E",
    "submission_id": "CF122592591",
    "submission_url": "https://codeforces.com/contest/1547/submission/122592591",
    "tags": [
      "data structures",
      "dp",
      "implementation",
      "shortest paths",
      "sortings",
      "two pointers",
      "*1500"
    ],
    "timestamp": "Jul/15/2021 20:02"
  },
  "CF123217749": {
    "contest_id": 15,
    "language": "GNU C++17 (64)",
    "path": "codeforces\\15\\A.cpp",
    "platform": "Codeforces",
    "problem_index": "A",
    "problem_name": "Cottage Village",
    "problem_url": "https://codeforces.com/contest/15/problem/A",
    "submission_id": "CF123217749",
    "submission_url": "https://codeforces.com/contest/15/submission/123217749",
    "tags": [
      "implementation",
      "sortings",
      "*1200"
    ],
    "timestamp": "Jul/22/2021 00:37"
  },
  "CF123246650": {
    "contest_id": 34,
    "language": "Python 3",
    "path": "codeforces\\34\\A.py",
    "platform": "Codeforces",
    "problem_index": "A",
    "problem_name": "Reconnaissance 2",
    "problem_url": "https://codeforces.com/contest/34/problem/A",
    "submission_id": "CF123246650",
    "submission_url": "https://codeforces.com/contest/34/submission/123246650",
    "tags": [
      "implementation",
      "*800"
    ],
    "timestamp": "Jul/22/2021 12:19"
  },
  "CF123246749": {
    "contest_id": 34,
    "language": "PyPy 3",
    "path": "codeforces\\34\\A.py",
    "platform": "Codeforces",
    "problem_index": "A",
    "problem_name": "Reconnaissance 2",
    "problem_url": "https://codeforces.com/contest/34/problem/A",
    "submission_id": "CF123246749",
    "submission_url": "https://codeforces.com/contest/34/submission/123246749",
    "tags": [
      "implementation",
      "*800"
    ],
    "timestamp": "Jul/22/2021 12:20"
  },
  "CF123345805": {
    "contest_id": 24,
    "language": "GNU C++17 (64)",
    "path": "codeforces\\24\\B.cpp",
    "platform": "Codeforces",
    "problem_index": "B",
    "problem_name": "F1 Champions",
    "problem_url": "https://codeforces.com/contest/24/problem/B",
    "submission_id": "CF123345805",
    "submission_url": "https://codeforces.com/contest/24/submission/123345805",
    "tags": [],
    "timestamp": "Jul/22/2021 22:46"
  },
  "CF123389183": {
    "contest_id": 24,
    "language": "GNU C++17 (64)",
    "path": "codeforces\\24\\B.cpp",
    "platform": "Codeforces",
    "problem_index": "B",
    "problem_name": "F1 Champions",
    "problem_url": "https://codeforces.com/contest/24/problem/B",
    "submission_id": "CF123389183",
    "submission_url": "https://codeforces.com/contest/24/submission/123389183",
    "tags": [
      "implementation",
      "*1500"
    ],
    "timestamp": "Jul/23/2021 10:31"
  },
  "CF123444730": {
    "contest_id": 1551,
    "language": "GNU C++17 (64)",
    "path": "codeforces\\1551\\A.cpp",
    "platform": "Codeforces",
    "problem_index": "A",
    "problem_name": "Polycarp and Coins",
    "problem_url": "https://codeforces.com/contest/1551/problem/A",
    "submission_id": "CF123444730",
    "submission_url": "https://codeforces.com/contest/1551/submission/123444730",
    "tags": [
      "greedy",
      "math",
      "*800"
    ],
    "timestamp": "Jul/23/2021 20:37"
  },
  "CF123460092": {
    "contest_id": 1551,
    "language": "GNU C++17 (64)",
    "path": "codeforces\\1551\\B1.cpp",
    "platform": "Codeforces",
    "problem_index": "B1",
    "problem_name": "Wonderful Coloring - 1",
    "problem_url": "https://codeforces.com/contest/1551/problem/B1",
    "submission_id": "CF123460092",
    "submission_url": "https://codeforces.com/contest/1551/submission/123460092",
    "tags": [
      "greedy",
      "strings",
      "*800"
    ],
    "timestamp": "Jul/23/2021 20:48"
  },
  "CF123519792": {
    "contest_id": 1551,
    "language": "GNU C++17 (64)",
    "path": "codeforces\\1551\\B2.cpp",
    "platform": "Codeforces",
    "problem_index": "B2",
    "problem_name": "Wonderful Coloring - 2",
    "problem_url": "https://codeforces.com/contest/1551/problem/B2",
    "submission_id": "CF123519792",
    "submission_url": "https://codeforces.com/contest/1551/submission/123519792",
    "tags": [
      "binary search",
      "constructive algorithms",
      "data structures",
      "greedy",
      "*1400"
    ],
    "timestamp": "Jul/23/2021 22:20"
  },
  "CF123539400": {
    "contest_id": 1551,
    "language": "GNU C++17 (64)",
    "path": "codeforces\\1551\\C.cpp",
    "platform": "Codeforces",
    "problem_index": "C",
    "problem_name": "Interesting Story",
    "problem_url": "https://codeforces.com/contest/1551/problem/C",
    "submission_id": "CF123539400",
    "submission_url": "https://codeforces.com/contest/1551/submission/123539400",
    "tags": [
      "greedy",
      "sortings",
      "strings",
      "*1500"
    ],
    "timestamp": "Jul/24/2021 00:15"
  },
  "CF123994362": {
    "contest_id": 1551,
    "language": "GNU C++17 (64)",
    "path": "codeforces\\1551\\D1.cpp",
    "platform": "Codeforces",
    "problem_index": "D1",
    "problem_name": "Domino (easy version)",
    "problem_url": "https://codeforces.com/contest/1551/problem/D1",
    "submission_id": "CF123994362",
    "submission_url": "https://codeforces.com/contest/1551/submission/123994362",
    "tags": [
      "constructive algorithms",
      "math",
      "*1700"
    ],
    "timestamp": "Jul/28/2021 11:38"
  },
  "CF124131564": {
    "contest_id": 1554,
    "language": "GNU C++17 (64)",
    "path": "codeforces\\1554\\A.cpp",
    "platform": "Codeforces",
    "problem_index": "A",
    "problem_name": "Cherry",
    "problem_url": "https://codeforces.com/contest/1554/problem/A",
    "submission_id": "CF124131564",
    "submission_url": "https://codeforces.com/contest/1554/submission/124131564",
    "tags": [
      "greedy",
      "*800"
    ],
    "timestamp": "Jul/29/2021 20:40"
  },
  "CF124293485": {
    "contest_id": 1555,
    "language": "GNU C++17 (64)",
    "path": "codeforces\\1555\\A.cpp",
    "platform": "Codeforces",
    "problem_index": "A",
    "problem_name": "PizzaForces",
    "problem_url": "https://codeforces.com/contest/1555/problem/A",
    "submission_id": "CF124293485",
    "submission_url": "https://codeforces.com/contest/1555/submission/124293485",
    "tags": [
      "brute force",
      "math",
      "*900"
    ],
    "timestamp": "Jul/30/2021 20:58"
  },
  "CF124320984": {
    "contest_id": 1555,
    "language": "GNU C++17 (64)",
    "path": "codeforces\\1555\\C.cpp",
    "platform": "Codeforces",
    "problem_index": "C",
    "problem_name": "Coin Rows",
    "problem_url": "https://codeforces.com/contest/1555/problem/C",
    "submission_id": "CF124320984",
    "submission_url": "https://codeforces.com/contest/1555/submission/124320984",
    "tags": [
      "brute force",
      "constructive algorithms",
      "dp",
      "implementation",
      "*1300"
    ],
    "timestamp": "Jul/30/2021 21:45"
  },
  "CF124333446": {
    "contest_id": 1555,
    "language": "GNU C++17 (64)",
    "path": "codeforces\\1555\\B.cpp",
    "platform": "Codeforces",
    "problem_index": "B",
    "problem_name": "Two Tables",
    "problem_url": "https://codeforces.com/contest/1555/problem/B",
    "submission_id": "CF124333446",
    "submission_url": "https://codeforces.com/contest/1555/submission/124333446",
    "tags": [
      "brute force",
      "*1300"
    ],
    "timestamp": "Jul/30/2021 22:14"
  },
  "CF125069057": {
    "contest_id": 266,
    "language": "GNU C++17 (64)",
    "path": "codeforces\\266\\B.cpp",
    "platform": "Codeforces",
    "problem_index": "B",
    "problem_name": "Queue at the School",
    "problem_url": "https://codeforces.com/contest/266/problem/B",
    "submission_id": "CF125069057",
    "submission_url": "https://codeforces.com/contest/266/submission/125069057",
    "tags": [
      "constructive algorithms",
      "graph matchings",
      "implementation",
      "shortest paths",
      "*800"
    ],
    "timestamp": "Aug/06/2021 21:45"
  },
  "CF125070418": {
    "contest_id": 339,
    "language": "GNU C++17 (64)",
    "path": "codeforces\\339\\B.cpp",
    "platform": "Codeforces",
    "problem_index": "B",
    "problem_name": "Xenia and Ringroad",
    "problem_url": "https://codeforces.com/contest/339/problem/B",
    "submission_id": "CF125070418",
    "submission_url": "https://codeforces.com/contest/339/submission/125070418",
    "tags": [
      "implementation",
      "*1000"
    ],
    "timestamp": "Aug/06/2021 22:00"
  },
  "CF125072954": {
    "contest_id": 467,
    "language": "GNU C++17 (64)",
    "path": "codeforces\\467\\B.cpp",
    "platform": "Codeforces",
    "problem_index": "B",
    "problem_name": "Fedor and New Game",
    "problem_url": "https://codeforces.com/contest/467/problem/B",
    "submission_id": "CF125072954",
    "submission_url": "https://codeforces.com/contest/467/submission/125072954",
    "tags": [
      "bitmasks",
      "brute force",
      "constructive algorithms",
      "implementation",
      "*1100"
    ],
    "timestamp": "Aug/06/2021 22:32"
  },
  "CF125077389": {
    "contest_id": 478,
    "language": "GNU C++17 (64)",
    "path": "codeforces\\478\\B.cpp",
    "platform": "Codeforces",
    "problem_index": "B",
    "problem_name": "Random Teams",
    "problem_url": "https://codeforces.com/contest/478/problem/B",
    "submission_id": "CF125077389",
    "submission_url": "https://codeforces.com/contest/478/submission/125077389",
    "tags": [
      "combinatorics",
      "constructive algorithms",
      "greedy",
      "math",
      "*1300"
    ],
    "timestamp": "Aug/06/2021 23:24"
  },
  "CF125811884": {
    "contest_id": 1554,
    "language": "GNU C++17 (64)",
    "path": "codeforces\\1554\\B.cpp",
    "platform": "Codeforces",
    "problem_index": "B",
    "problem_name": "Cobb",
    "problem_url": "https://codeforces.com/contest/1554/problem/B",
    "submission_id": "CF125811884",
    "submission_url": "https://codeforces.com/contest/1554/submission/125811884",
    "tags": [
      "bitmasks",
      "brute force",
      "greedy",
      "math",
      "*1700"
    ],
    "timestamp": "Aug/14/2021 09:37"
  },
  "CF125873094": {
    "contest_id": 492,
    "language": "GNU C++17 (64)",
    "path": "codeforces\\492\\B.cpp",
    "platform": "Codeforces",
    "problem_index": "B",
    "problem_name": "Vanya and Lanterns",
    "problem_url": "https://codeforces.com/contest/492/problem/B",
    "submission_id": "CF125873094",
    "submission_url": "https://codeforces.com/contest/492/submission/125873094",
    "tags": [
      "binary search",
      "implementation",
      "math",
      "sortings",
      "*1200"
    ],
    "timestamp": "Aug/15/2021 00:15"
  },
  "CF126556879": {
    "contest_id": 451,
    "language": "GNU C++17 (64)",
    "path": "codeforces\\451\\B.cpp",
    "platform": "Codeforces",
    "problem_index": "B",
    "problem_name": "Sort the Array",
    "problem_url": "https://codeforces.com/contest/451/problem/B",
    "submission_id": "CF126556879",
    "submission_url": "https://codeforces.com/contest/451/submission/126556879",
    "tags": [
      "implementation",
      "sortings",
      "*1300"
    ],
    "timestamp": "Aug/20/2021 22:32"
  },
  "CF126727361": {
    "contest_id": 230,
    "language": "GNU C++17 (64)",
    "path": "codeforces\\230\\B.cpp",
    "platform": "Codeforces",
    "problem_index": "B",
    "problem_name": "T-primes",
    "problem_url": "https://codeforces.com/contest/230/problem/B",
    "submission_id": "CF126727361",
    "submission_url": "https://codeforces.com/contest/230/submission/126727361",
    "tags": [
      "binary search",
      "implementation",
      "math",
      "number theory",
      "*1300"
    ],
    "timestamp": "Aug/23/2021 10:23"
  },
  "CF127341466": {
    "contest_id": 1556,
    "language": "GNU C++17 (64)",
    "path": "codeforces\\1556\\A.cpp",
    "platform": "Codeforces",
    "problem_index": "A",
    "problem_name": "A Variety of Operations",
    "problem_url": "https://codeforces.com/contest/1556/problem/A",
    "submission_id": "CF127341466",
    "submission_url": "https://codeforces.com/contest/1556/submission/127341466",
    "tags": [
      "math",
      "*800"
    ],
    "timestamp": "Aug/29/2021 20:44"
  },
  "CF127351468": {
    "contest_id": 1556,
    "language": "GNU C++17 (64)",
    "path": "codeforces\\1556\\B.cpp",
    "platform": "Codeforces",
    "problem_index": "B",
    "problem_name": "Take Your Places!",
    "problem_url": "https://codeforces.com/contest/1556/problem/B",
    "submission_id": "CF127351468",
    "submission_url": "https://codeforces.com/contest/1556/submission/127351468",
    "tags": [
      "implementation",
      "*1300"
    ],
    "timestamp": "Aug/29/2021 21:03"
  },
  "CF128090751": {
    "contest_id": 1567,
    "language": "GNU C++17 (64)",
    "path": "codeforces\\1567\\A.cpp",
    "platform": "Codeforces",
    "problem_index": "A",
    "problem_name": "Domino Disaster",
    "problem_url": "https://codeforces.com/contest/1567/problem/A",
    "submission_id": "CF128090751",
    "submission_url": "https://codeforces.com/contest/1567/submission/128090751",
    "tags": [
      "implementation",
      "strings",
      "*800"
    ],
    "timestamp": "Sep/07/2021 09:14"
  },
  "CF128308994": {
    "contest_id": 1567,
    "language": "GNU C++17 (64)",
    "path": "codeforces\\1567\\B.cpp",
    "platform": "Codeforces",
    "problem_index": "B",
    "problem_name": "MEXor Mixup",
    "problem_url": "https://codeforces.com/contest/1567/problem/B",
    "submission_id": "CF128308994",
    "submission_url": "https://codeforces.com/contest/1567/submission/128308994",
    "tags": [
      "bitmasks",
      "greedy",
      "*1000"
    ],
    "timestamp": "Sep/09/2021 09:45"
  },
  "CF129013585": {
    "contest_id": 508,
    "language": "GNU C++17 (64)",
    "path": "codeforces\\508\\B.cpp",
    "platform": "Codeforces",
    "problem_index": "B",
    "problem_name": "Anton and currency you all know",
    "problem_url": "https://codeforces.com/contest/508/problem/B",
    "submission_id": "CF129013585",
    "submission_url": "https://codeforces.com/contest/508/submission/129013585",
    "tags": [
      "greedy",
      "math",
      "strings",
      "*1300"
    ],
    "timestamp": "Sep/17/2021 00:00"
  },
  "CF129096297": {
    "contest_id": 71,
    "language": "GNU C++17 (64)",
    "path": "codeforces\\71\\A.cpp",
    "platform": "Codeforces",
    "problem_index": "A",
    "problem_name": "Way Too Long Words",
    "problem_url": "https://codeforces.com/contest/71/problem/A",
    "submission_id": "CF129096297",
    "submission_url": "https://codeforces.com/contest/71/submission/129096297",
    "tags": [
      "strings",
      "*800"
    ],
    "timestamp": "Sep/17/2021 23:29"
  },
  "CF129098149": {
    "contest_id": 339,
    "language": "GNU C++17 (64)",
    "path": "codeforces\\339\\A.cpp",
    "platform": "Codeforces",
    "problem_index": "A",
    "problem_name": "Helpful Maths",
    "problem_url": "https://codeforces.com/contest/339/problem/A",
    "submission_id": "CF129098149",
    "submission_url": "https://codeforces.com/contest/339/submission/129098149",
    "tags": [
      "greedy",
      "implementation",
      "sortings",
      "strings",
      "*800"
    ],
    "timestamp": "Sep/17/2021 23:49"
  },
  "CF129101750": {
    "contest_id": 160,
    "language": "GNU C++17 (64)",
    "path": "codeforces\\160\\A.cpp",
    "platform": "Codeforces",
    "problem_index": "A",
    "problem_name": "Twins",
    "problem_url": "https://codeforces.com/contest/160/problem/A",
    "submission_id": "CF129101750",
    "submission_url": "https://codeforces.com/contest/160/submission/129101750",
    "tags": [
      "greedy",
      "sortings",
      "*900"
    ],
    "timestamp": "Sep/18/2021 00:33"
  },
  "CF129102431": {
    "contest_id": 58,
    "language": "GNU C++17 (64)",
    "path": "codeforces\\58\\A.cpp",
    "platform": "Codeforces",
    "problem_index": "A",
    "problem_name": "Chat room",
    "problem_url": "https://codeforces.com/contest/58/problem/A",
    "submission_id": "CF129102431",
    "submission_url": "https://codeforces.com/contest/58/submission/129102431",
    "tags": [
      "greedy",
      "strings",
      "*1000"
    ],
    "timestamp": "Sep/18/2021 00:43"
  }
}